COPYING
MANIFEST.in
README.rst
bootstrap.py
buildout.cfg
setup.py
docs/bimodal_experiments.rst
docs/conf.py
docs/face_experiments.rst
docs/index.rst
docs/installation.rst
docs/miris.rst
docs/speaker_experiments.rst
xbob/__init__.py
xbob.thesis.elshafey2014.egg-info/PKG-INFO
xbob.thesis.elshafey2014.egg-info/SOURCES.txt
xbob.thesis.elshafey2014.egg-info/dependency_links.txt
xbob.thesis.elshafey2014.egg-info/entry_points.txt
xbob.thesis.elshafey2014.egg-info/namespace_packages.txt
xbob.thesis.elshafey2014.egg-info/not-zip-safe
xbob.thesis.elshafey2014.egg-info/requires.txt
xbob.thesis.elshafey2014.egg-info/top_level.txt
xbob/thesis/__init__.py
xbob/thesis/elshafey2014/__init__.py
xbob/thesis/elshafey2014/configurations/__init__.py
xbob/thesis/elshafey2014/configurations/default.py
xbob/thesis/elshafey2014/configurations/gmm1024.py
xbob/thesis/elshafey2014/configurations/grid/__init__.py
xbob/thesis/elshafey2014/configurations/grid/grid_16G.py
xbob/thesis/elshafey2014/configurations/grid/grid_24G.py
xbob/thesis/elshafey2014/configurations/grid/grid_score.py
xbob/thesis/elshafey2014/configurations/grid/grid_w16G.py
xbob/thesis/elshafey2014/configurations/grid/grid_w24G.py
xbob/thesis/elshafey2014/configurations/grid/grid_w32G.py
xbob/thesis/elshafey2014/configurations/grid/para_grid.py
xbob/thesis/elshafey2014/configurations/grid/para_grid_dct.py
xbob/thesis/elshafey2014/configurations/grid/para_grid_gmm1024.py
xbob/thesis/elshafey2014/configurations/grid/para_grid_ivector.py
xbob/thesis/elshafey2014/databases/DatabaseXBobZT_TNorm.py
xbob/thesis/elshafey2014/databases/__init__.py
xbob/thesis/elshafey2014/databases/arface.py
xbob/thesis/elshafey2014/databases/banca.py
xbob/thesis/elshafey2014/databases/caspeal.py
xbob/thesis/elshafey2014/databases/frgc.py
xbob/thesis/elshafey2014/databases/gbu.py
xbob/thesis/elshafey2014/databases/lfw.py
xbob/thesis/elshafey2014/databases/lfwidentification.py
xbob/thesis/elshafey2014/databases/mobio_female.py
xbob/thesis/elshafey2014/databases/mobio_male.py
xbob/thesis/elshafey2014/databases/multipie.py
xbob/thesis/elshafey2014/databases/nist_sre12_female.py
xbob/thesis/elshafey2014/databases/nist_sre12_gd_female.py
xbob/thesis/elshafey2014/databases/nist_sre12_gd_male.py
xbob/thesis/elshafey2014/databases/nist_sre12_male.py
xbob/thesis/elshafey2014/scripts/__init__.py
xbob/thesis/elshafey2014/scripts/cosine_distance.py
