Metadata-Version: 1.1
Name: xbob.thesis.elshafey2014
Version: 0.0.1a0
Summary: Experiments of Laurent El Shafey's Ph.D. thesis
Home-page: https://pypi.python.org/pypi/xbob.thesis.elshafey2014
Author: Laurent El Shafey
Author-email: Laurent.El-Shafey@idiap.ch
License: GPLv3
Keywords: bob,xbob,face recognition,speaker recognition,bimodal recognition,facereclib,xbob.spkrec,GMM,ISV,JFA,TV,i-vector,PLDA,EPFL,Idiap
Platform: UNKNOWN
Classifier: Development Status :: 3 - Alpha
Classifier: Intended Audience :: Developers
Classifier: License :: OSI Approved :: GNU General Public License v3 (GPLv3)
Classifier: Natural Language :: English
Classifier: Programming Language :: Python
Classifier: Topic :: Scientific/Engineering :: Artificial Intelligence
